LICENSE
MANIFEST.in
README.rst
setup.py
il2fb/ds/airbridge/__init__.py
il2fb/ds/airbridge/application.py
il2fb/ds/airbridge/compat.py
il2fb/ds/airbridge/config.py
il2fb/ds/airbridge/exceptions.py
il2fb/ds/airbridge/json.py
il2fb/ds/airbridge/logging.py
il2fb/ds/airbridge/main.py
il2fb/ds/airbridge/nats.py
il2fb/ds/airbridge/radar.py
il2fb/ds/airbridge/state.py
il2fb/ds/airbridge/structures.py
il2fb/ds/airbridge/terminal.py
il2fb/ds/airbridge/tls.py
il2fb/ds/airbridge/typing.py
il2fb/ds/airbridge/watch_dog.py
il2fb/ds/airbridge/api/__init__.py
il2fb/ds/airbridge/api/nats.py
il2fb/ds/airbridge/api/http/__init__.py
il2fb/ds/airbridge/api/http/constants.py
il2fb/ds/airbridge/api/http/routes.py
il2fb/ds/airbridge/api/http/security.py
il2fb/ds/airbridge/api/http/responses/__init__.py
il2fb/ds/airbridge/api/http/responses/rest.py
il2fb/ds/airbridge/api/http/responses/ws.py
il2fb/ds/airbridge/api/http/views/__init__.py
il2fb/ds/airbridge/api/http/views/chat.py
il2fb/ds/airbridge/api/http/views/humans.py
il2fb/ds/airbridge/api/http/views/misc.py
il2fb/ds/airbridge/api/http/views/missions.py
il2fb/ds/airbridge/api/http/views/radar.py
il2fb/ds/airbridge/api/http/views/streaming.py
il2fb/ds/airbridge/dedicated_server/__init__.py
il2fb/ds/airbridge/dedicated_server/console.py
il2fb/ds/airbridge/dedicated_server/device_link.py
il2fb/ds/airbridge/dedicated_server/game_log.py
il2fb/ds/airbridge/dedicated_server/instance.py
il2fb/ds/airbridge/dedicated_server/path.py
il2fb/ds/airbridge/dedicated_server/validators.py
il2fb/ds/airbridge/streaming/__init__.py
il2fb/ds/airbridge/streaming/facilities.py
il2fb/ds/airbridge/streaming/subscribers/__init__.py
il2fb/ds/airbridge/streaming/subscribers/base.py
il2fb/ds/airbridge/streaming/subscribers/file.py
il2fb/ds/airbridge/streaming/subscribers/loaders.py
il2fb/ds/airbridge/streaming/subscribers/nats.py
il2fb_ds_airbridge.egg-info/PKG-INFO
il2fb_ds_airbridge.egg-info/SOURCES.txt
il2fb_ds_airbridge.egg-info/dependency_links.txt
il2fb_ds_airbridge.egg-info/entry_points.txt
il2fb_ds_airbridge.egg-info/namespace_packages.txt
il2fb_ds_airbridge.egg-info/requires.txt
il2fb_ds_airbridge.egg-info/top_level.txt
requirements/dist-windows.txt
requirements/dist.txt