Metadata-Version: 1.1
Name: il2fb-ds-airbridge
Version: 1.0.0
Summary: Wrapper of dedicated server of «IL-2 Sturmovik: Forgotten Battles»
Home-page: https://github.com/IL2HorusTeam/il2fb-ds-airbridge
Author: Alexander Oblovatniy
Author-email: oblovatniy@gmail.com
License: MIT
Platform: UNKNOWN
Classifier: Programming Language :: Python :: 3.6
Classifier: Operating System :: Unix
Classifier: Operating System :: Microsoft :: Windows
Classifier: License :: OSI Approved :: MIT License
Classifier: Development Status :: 5 - Production/Stable
Classifier: Topic :: Communications
Classifier: Topic :: Games/Entertainment :: Simulation
Classifier: Environment :: Console
Classifier: Intended Audience :: System Administrators
Classifier: Natural Language :: English
